README.md
pyproject.toml
setup.cfg
setup.py
django_payments_portmone.egg-info/PKG-INFO
django_payments_portmone.egg-info/SOURCES.txt
django_payments_portmone.egg-info/dependency_links.txt
django_payments_portmone.egg-info/requires.txt
django_payments_portmone.egg-info/top_level.txt
payments_portmone/__init__.py
payments_portmone/forms.py
payments_portmone/provider.py
payments_portmone/service.py