Metadata-Version: 2.1
Name: django-payments-portmone
Version: 0.1.1
Summary: A django-payments backend for the Portmone payment gateway
Home-page: https://github.com/onufrienkovi/django-payments-portmone
Author: Vyacheslav Onufrienko
Author-email: onufrienkovi@gmail.com
License: UNKNOWN
Platform: UNKNOWN
Classifier: Environment :: Web Environment
Classifier: Framework :: Django
Classifier: Intended Audience :: Developers
Classifier: Operating System :: OS Independent
Classifier: Programming Language :: Python
Classifier: Programming Language :: Python :: 3.6
Classifier: Programming Language :: Python :: 3.7
Classifier: Programming Language :: Python :: 3.8
Classifier: Topic :: Internet :: WWW/HTTP
Classifier: Topic :: Software Development :: Libraries :: Application Frameworks
Classifier: Topic :: Software Development :: Libraries :: Python Modules
Requires-Python: >=3.6
Provides-Extra: test
Provides-Extra: lint
Provides-Extra: dev
